deep3/__init__.py
deep3/api_client.py
deep3/api_response.py
deep3/configuration.py
deep3/exceptions.py
deep3/rest.py
deep3/api/__init__.py
deep3/api/deep3_api.py
deep3/models/__init__.py
deep3/models/chains_response.py
deep3/models/chains_response_inner.py
deep3/models/deep_shield_fr_response.py
deep3/models/deep_shield_hft_response.py
deep3/models/get_chains_result.py
deep3/models/get_hodl_c1_response.py
deep3/models/get_hodler_result.py
deep3/models/get_models_result.py
deep3/models/get_prediction_result.py
deep3/models/get_stake_sage_h_response.py
deep3/models/get_stake_sage_l_response.py
deep3/models/hodl_c1_response.py
deep3/models/hodl_c1_x_token_request.py
deep3/models/hodl_c1_x_token_request_mappings_inner.py
deep3/models/hodl_c1_x_token_response.py
deep3/models/hodl_c1_x_tokens_request.py
deep3/models/hodl_c1_x_tokens_request_addresses_inner.py
deep3/models/hodl_c1_x_tokens_response_inner.py
deep3/models/hodler_response.py
deep3/models/models_response.py
deep3/models/models_response_inner.py
deep3/models/post_hodl_c1_x_token_request.py
deep3/models/post_hodl_c1_x_token_request_mappings_inner.py
deep3/models/post_hodl_c1_x_token_response.py
deep3/models/post_hodl_c1_x_tokens_request.py
deep3/models/post_hodl_c1_x_tokens_request_addresses_inner.py
deep3/models/post_hodl_c1_x_tokens_response_inner.py
deep3/models/prediction_response.py
deep3/models/stake_sage_c_response.py
deep3/models/stake_sage_h_response.py
deep3/models/stake_sage_l_response.py
deep3_python_client-0.0.4.dist-info/METADATA
deep3_python_client-0.0.4.dist-info/WHEEL
deep3_python_client-0.0.4.dist-info/top_level.txt
deep3_python_client-0.0.4.dist-info/RECORD
