Metadata-Version: 2.1
Name: deep3-python-client
Version: 0.0.4
Summary: Deep3 Labs Python API client
Home-page: https://github.com/deep3labs/deep3-python-client.git
Author: Deep3 Labs
Author-email: hello@deep3.ai
Keywords: deep3labs,web3,blockchain,ml,ai
Requires-Dist: urllib3 >=1.25.3
Requires-Dist: python-dateutil
Requires-Dist: pydantic <2,>=1.10.5
Requires-Dist: aenum
